pyaton.py
pyaton-0.0.5.dist-info/LICENSE
pyaton-0.0.5.dist-info/METADATA
pyaton-0.0.5.dist-info/WHEEL
pyaton-0.0.5.dist-info/top_level.txt
pyaton-0.0.5.dist-info/RECORD
