Metadata-Version: 2.1
Name: pyaton
Version: 0.0.5
Summary: Get informations about your Aton Green Storage solar panel system
Author: Luca Patarca
Classifier: Programming Language :: Python :: 3
Classifier: License :: OSI Approved :: MIT License
Classifier: Operating System :: OS Independent
Requires-Python: >=3.6
License-File: LICENSE
Requires-Dist: fake-useragent (>=1.1.1)
